{
  "criteria": {
    "clothes": {
      "conditions": {
        "items": [
          {
            "items": [
              "butterflies:bottled_caterpillar_clothes"
            ]
          }
        ]
      },
      "trigger": "minecraft:inventory_changed"
    },
    "luna": {
      "conditions": {
        "items": [
          {
            "items": [
              "butterflies:bottled_caterpillar_luna"
            ]
          }
        ]
      },
      "trigger": "minecraft:inventory_changed"
    }
  },
  "display": {
    "announce_to_chat": true,
    "description": {
      "translate": "advancements.butterfly.bottle_all_larvae.description"
    },
    "frame": "challenge",
    "hidden": false,
    "icon": {
      "item": "butterflies:bottled_caterpillar_clothes"
    },
    "show_toast": true,
    "title": {
      "translate": "advancements.butterfly.bottle_all_larvae.title"
    }
  },
  "parent": "butterflies:butterfly/bottle_larva",
  "requirements": [
    [
      "clothes"
    ],
    [
      "luna"
    ]
  ]
}